prints_utils/__init__.py
prints_utils/prints.py
prints_utils-0.5.0.dist-info/licenses/LICENSE
prints_utils-0.5.0.dist-info/METADATA
prints_utils-0.5.0.dist-info/WHEEL
prints_utils-0.5.0.dist-info/top_level.txt
prints_utils-0.5.0.dist-info/RECORD
