Metadata-Version: 2.4
Name: prints_utils
Version: 0.5.0
Summary: Librería de utilidades para prints en consola con colores
Author-email: Edinson Tunjano <juanmadiaz108@gmail.com>
License: MIT
Keywords: prints,colores,consola,utilidades
Classifier: Programming Language :: Python :: 3
Classifier: License :: OSI Approved :: MIT License
Classifier: Operating System :: OS Independent
Requires-Python: >=3.8
License-File: LICENSE
Requires-Dist: sqlalchemy
Dynamic: license-file
